distribute_setup.py
setup.py
bin/kegboard-info.py
bin/kegboard-monitor.py
bin/kegboard-tester.py
bin/set-kegboard-serialnumber
jrfork_kegbot_kegboard.egg-info/PKG-INFO
jrfork_kegbot_kegboard.egg-info/SOURCES.txt
jrfork_kegbot_kegboard.egg-info/dependency_links.txt
jrfork_kegbot_kegboard.egg-info/namespace_packages.txt
jrfork_kegbot_kegboard.egg-info/requires.txt
jrfork_kegbot_kegboard.egg-info/top_level.txt
kegbot/__init__.py
kegbot/kegboard/__init__.py
kegbot/kegboard/crc16.py
kegbot/kegboard/crc16_test.py
kegbot/kegboard/exceptions.py
kegbot/kegboard/kegboard.py
kegbot/kegboard/kegboard_test.py
kegbot/kegboard/message.py