Metadata-Version: 1.0
Name: jrfork-kegbot-kegboard
Version: 0.0.1
Summary: Johnnyruzdev Fork of the Kegboard support library.
Home-page: http://kegbot.org/
Author: johnnyruzdev
Author-email: johnnyruzdev01@outlook.com
License: UNKNOWN
Platform: UNKNOWN
